[
  {
    "University": "University of Georgia",
    "Faculty": "Wei Niu",
    "Research Interests": "ML System, High Performance Computing, Compiler Optimization",
    "Notes": "2025 Spring / Fall",
    "Homepage": "https://www.niuwei.info",
    "Positions": "2 PhDs RAs",
    "Requirements": "TOEFL, no GRE requirement",
    "How to Reach out": "Email",
    "@": ""
  },
  {
    "University": "University of Georgia",
    "Faculty": "Guoyu Lu",
    "Research Interests": "Robotics, computer vision, AI, ML",
    "Notes": "25 Spring / Fall",
    "Homepage": "",
    "Positions": "5-6 PhDs with RA",
    "Requirements": "TOEFL/IELTS/Duolingo, no GRE",
    "How to Reach out": "Email",
    "@": ""
  },
  {
    "University": "University of Georgia",
    "Faculty": "Zhenlin An",
    "Research Interests": "wireless and mobile computing, AI for networks, AR/VR",
    "Notes": "25 Fall, 26 Spring/Fall",
    "Homepage": "https://anplus.github.io/",
    "Positions": "2-3 PhDs with RA/TA",
    "Requirements": "TOEFL or IELTS, no GRE",
    "How to Reach out": "Email",
    "@": ""
  },
  {
    "University": "University of Georgia",
    "Faculty": "Haijian Sun",
    "Research Interests": "Generative models, AI for wireless, learning thoery",
    "Notes": "26 Spring/Fall",
    "Homepage": "https://sunlab.uga.edu",
    "Positions": "1-2 PhD with RA",
    "Requirements": "TOEFL or IELTS, no GRE",
    "How to Reach out": "Email",
    "@": ""
  }
]